{
  "Documentary": [
    {
      "name": "La_Une",
      "url": "https://c9851ec-rbm-hilv-fsly.cdn.redbee.live/L26/669bb376/9069a322.isml/.mpd",
      "key": "cbdd636bb2e44f1fa6ebd41f46a3cc52:e6ab6c56a79962dcab612e9dc4fea986",
      "logo": "https://upload.wikimedia.org/wikipedia/commons/a/a3/RTBF_La_Une_logo_2004.png",
      "user_agent": "Mozilla/5.0 (Windows NT 10.0; Win64; x64) AppleWebKit/537.36"
    },
    {
      "name": "Animal Planet",
      "url": "https://api-proxad.dc2.oqee.net/playlist/v1/live/973/1/live.mpd",
      "key": "{"kty":"oct","kid":"sEeP0mQk6I+h5keO411/CA","k":"9QRCQtjSJMrkCH/Y72VAIw"},{"kty":"oct","kid":"InUSnyhWdxReNOuL4kmuSg","k":"dQVcYFHWUMUpYnseYm9TCg"},{"kty":"oct","kid":"LrcsuNUlcZzdo+H1zEOzQg","k":"4Hl+IoZXVIcgUgFd2ikF9w"},{"kty":"oct","kid":"CtLb067+IHA08kBQ68mM0Q","k":"CxIf52nQsbRaOmu4xA40BQ"}]}",
      "logo": "https://i.ibb.co/s9yfNbx/beinmax5.png",
      "user_agent": "Dalvik/2.1.0 (Linux; U; Android 11; TV Box Build/RP1A.200720.011)"
    }
  ],
  "Entertainment": [
    {
      "name": "MBC 1 HD",
      "url": "https://video.beeline.tv/live/d/channel319.isml/manifest-stb.mpd",
      "key": "9145a6e0f778e61866f573d4944dd533:d02173d40515fea5c83944f21d0f3114",
      "logo": "https://new.matchtv.ru/assets/202507251502/images/channels/8.jpg",
      "user_agent": "Mozilla/5.0"
    }
  ],
  "Kids": [
    {
      "name": "SpaceToon",
      "url": "https://uselector.cdn.intigral-ott.net/SPT/SPT.isml/manifest.mpd",
      "key": "2d61037244f336e8b8daf832ffc84003:999b547e5fdd56948315382730852045",
      "logo": "https://upload.wikimedia.org/wikipedia/ar/thumb/9/90/Spacetoon_Logo.svg/1200px-Spacetoon_Logo.svg.png",
      "user_agent": "Mozilla/5.0"
    }
  ],
  "Movies": [
    {
      "name": "STAR Movies",
      "url": "https://uselector.cdn.intigral-ott.net/STM/STM.isml/manifest.mpd",
      "key": "4b7a662d7132679630f3a3f1862a859c:0651bc37e705349a2848278ae3ad7bf4",
      "logo": "https://upload.wikimedia.org/wikipedia/commons/thumb/c/c5/Star_Movies_logo.svg/1200px-Star_Movies_logo.svg.png",
      "user_agent": "Mozilla/5.0"
    }
  ]
}
